tfold/__init__.py
tfold/config/__init__.py
tfold/config/build.py
tfold/config/config_node.py
tfold/config/default.py
tfold/config/utils.py
tfold/deploy/__init__.py
tfold/deploy/ab_predictor.py
tfold/deploy/ag_predictor.py
tfold/deploy/base_structure_predictor.py
tfold/deploy/plm_complex_predictor.py
tfold/deploy/psp_featurizer.py
tfold/deploy/tcr_predictor.py
tfold/model/__init__.py
tfold/model/build.py
tfold/model/pretrain.py
tfold/model/arch/__init__.py
tfold/model/arch/base_model.py
tfold/model/arch/complex_structure_model.py
tfold/model/arch/ppi_model.py
tfold/model/arch/ag_model/__init__.py
tfold/model/arch/ag_model/docking_model.py
tfold/model/arch/ag_model/model.py
tfold/model/arch/ag_model/mono_to_multimer.py
tfold/model/arch/alphafold/__init__.py
tfold/model/arch/alphafold/auxiliary_head.py
tfold/model/arch/alphafold/model.py
tfold/model/arch/alphafold/module/__init__.py
tfold/model/arch/alphafold/module/head.py
tfold/model/arch/alphafold/module/embedding/__init__.py
tfold/model/arch/alphafold/module/embedding/extra_msa_stack.py
tfold/model/arch/alphafold/module/embedding/input_embedding.py
tfold/model/arch/alphafold/module/embedding/msa_embedding.py
tfold/model/arch/alphafold/module/embedding/recyling_embedding.py
tfold/model/arch/alphafold/module/embedding/relative_position_embedding.py
tfold/model/arch/alphafold/module/embedding/template_embedding.py
tfold/model/arch/alphafold/module/structure_module/__init__.py
tfold/model/arch/alphafold/module/structure_module/protein_mapper.py
tfold/model/arch/alphafold/module/structure_module/structure_module.py
tfold/model/arch/core/__init__.py
tfold/model/arch/core/complex_lite_model.py
tfold/model/arch/core/complex_structure_model.py
tfold/model/arch/core/docking_model.py
tfold/model/arch/core/mono_to_multimer.py
tfold/model/arch/core/ppi_model.py
tfold/model/arch/core/module/__init__.py
tfold/model/arch/core/module/invariant_point_attention.py
tfold/model/arch/core/module/pair_predictor.py
tfold-1.0.2.dist-info/LICENSE
tfold-1.0.2.dist-info/METADATA
tfold-1.0.2.dist-info/WHEEL
tfold-1.0.2.dist-info/top_level.txt
tfold-1.0.2.dist-info/zip-safe
tfold-1.0.2.dist-info/RECORD
