Metadata-Version: 2.2
Name: tfold
Version: 1.0.2
Summary: Tencent Protein Predication Library
Author: Tencent AI for Life Sciences Lab
Author-email: chenchenqin@tencent.com
License-File: LICENSE
Provides-Extra: tfold
Requires-Dist: torch>=2.0; extra == "tfold"
Requires-Dist: deepspeed>=0.12.3; extra == "tfold"
Requires-Dist: termcolor>=2.3.0; extra == "tfold"
Requires-Dist: biopython>=1.79; extra == "tfold"
Requires-Dist: ml-collections>=0.1.1; extra == "tfold"
Requires-Dist: dm-tree>=0.1.8; extra == "tfold"
Requires-Dist: numpy>=1.21.2; extra == "tfold"
Requires-Dist: modelcif>=0.9; extra == "tfold"
Requires-Dist: scipy; extra == "tfold"
Dynamic: author
Dynamic: author-email
Dynamic: description
Dynamic: description-content-type
Dynamic: provides-extra
Dynamic: summary
